<?xml version="1.0" encoding="UTF-8"?>
<data>
	<node>
		<column_1><![CDATA[Cipro 500 Tablet 10]]></column_1>
		<column_2><![CDATA[Ciprofloxacin 500mg]]></column_2>
		<column_3><![CDATA[Clarion]]></column_3>
		<column_4><![CDATA[1]]></column_4>
		<column_5><![CDATA[321]]></column_5>
	</node>
	<node>
		<column_1><![CDATA[Acem Tablets 10]]></column_1>
		<column_2><![CDATA[Clarithromycin USP 500mg]]></column_2>
		<column_3><![CDATA[Clarion]]></column_3>
		<column_4><![CDATA[4]]></column_4>
		<column_5><![CDATA[850]]></column_5>
	</node>
	<node>
		<column_1><![CDATA[Ciprobiotic Forte tablet 10]]></column_1>
		<column_2><![CDATA[Ciprofloxacin 500mg]]></column_2>
		<column_3><![CDATA[Clarion]]></column_3>
		<column_4><![CDATA[4]]></column_4>
		<column_5><![CDATA[200]]></column_5>
	</node>
	<node>
		<column_1><![CDATA[C-Tax P 100ml]]></column_1>
		<column_2><![CDATA[Cefixime 50mg/5ml dry suspension]]></column_2>
		<column_3><![CDATA[Clarion]]></column_3>
		<column_4><![CDATA[4]]></column_4>
		<column_5><![CDATA[700]]></column_5>
	</node>
	<node>
		<column_1><![CDATA[Augpen suspension  100ml]]></column_1>
		<column_2><![CDATA[Amoxicillin 125mg, clavulinic acid 31.25mg]]></column_2>
		<column_3><![CDATA[Clarion]]></column_3>
		<column_4><![CDATA[4]]></column_4>
		<column_5><![CDATA[650]]></column_5>
	</node>
	<node>
		<column_1><![CDATA[C-Tax T 200 Tablet 10]]></column_1>
		<column_2><![CDATA[Cefixime trihydrate USP 200mg]]></column_2>
		<column_3><![CDATA[Clarion]]></column_3>
		<column_4><![CDATA[4]]></column_4>
		<column_5><![CDATA[700]]></column_5>
	</node>
	<node>
		<column_1><![CDATA[C-Tri injection  1 vial]]></column_1>
		<column_2><![CDATA[Ceftriaxone 1g]]></column_2>
		<column_3><![CDATA[clarion]]></column_3>
		<column_4><![CDATA[4]]></column_4>
		<column_5><![CDATA[250]]></column_5>
	</node>
	<node>
		<column_1><![CDATA[Qceph 250 Tablet]]></column_1>
		<column_2><![CDATA[Cefuroxime axetil USP 250mg]]></column_2>
		<column_3><![CDATA[Clarion]]></column_3>
		<column_4><![CDATA[4]]></column_4>
		<column_5><![CDATA[700]]></column_5>
	</node>
	<node>
		<column_1><![CDATA[Qceph 500]]></column_1>
		<column_2><![CDATA[Cefuroxime axetil USP 500mg]]></column_2>
		<column_3><![CDATA[Clarion]]></column_3>
		<column_4><![CDATA[4]]></column_4>
		<column_5><![CDATA[900]]></column_5>
	</node>
	<node>
		<column_1><![CDATA[Cerizine Tablet 10]]></column_1>
		<column_2><![CDATA[Levocetrizine 5mg]]></column_2>
		<column_3><![CDATA[Clarion]]></column_3>
		<column_4><![CDATA[4]]></column_4>
		<column_5><![CDATA[100]]></column_5>
	</node>
	<node>
		<column_1><![CDATA[Primpex suspension  50ml]]></column_1>
		<column_2><![CDATA[Trimethoprim 80mg, Sulphamethazole 400mg]]></column_2>
		<column_3><![CDATA[Clarion]]></column_3>
		<column_4><![CDATA[3]]></column_4>
		<column_5><![CDATA[222.72]]></column_5>
	</node>
	<node>
		<column_1><![CDATA[Primpex 960mg Tablet]]></column_1>
		<column_2><![CDATA[Trimethoprim 160mg, Sulphamethazole 800mg]]></column_2>
		<column_3><![CDATA[Clarion]]></column_3>
		<column_4><![CDATA[3]]></column_4>
		<column_5><![CDATA[201.51]]></column_5>
	</node>
	<node>
		<column_1><![CDATA[Primpex tablet 100]]></column_1>
		<column_2><![CDATA[Trimethoprim 80mg, Sulphamethazole 400mg]]></column_2>
		<column_3><![CDATA[Clarion]]></column_3>
		<column_4><![CDATA[3]]></column_4>
		<column_5><![CDATA[627.07]]></column_5>
	</node>
	<node>
		<column_1><![CDATA[Ziclox suspension  100ml]]></column_1>
		<column_2><![CDATA[Ampicillin 125mg, Cloxacillin 125mg/5ml]]></column_2>
		<column_3><![CDATA[Clarion]]></column_3>
		<column_4><![CDATA[3]]></column_4>
		<column_5><![CDATA[192.23]]></column_5>
	</node>
	<node>
		<column_1><![CDATA[Ziclox capsule 10]]></column_1>
		<column_2><![CDATA[Ampicillin 250mg, Cloxacillin 250mg]]></column_2>
		<column_3><![CDATA[Clarion]]></column_3>
		<column_4><![CDATA[3]]></column_4>
		<column_5><![CDATA[729.15]]></column_5>
	</node>
	<node>
		<column_1><![CDATA[Galcipro 500 10]]></column_1>
		<column_2><![CDATA[Ciprofloxacin 500mg]]></column_2>
		<column_3><![CDATA[Clarion]]></column_3>
		<column_4><![CDATA[3]]></column_4>
		<column_5><![CDATA[344.69]]></column_5>
	</node>
	<node>
		<column_1><![CDATA[Galcipro TN caplets 10]]></column_1>
		<column_2><![CDATA[Ciprofloxacin 500mg, Tinidazole 600mg]]></column_2>
		<column_3><![CDATA[Clarion]]></column_3>
		<column_4><![CDATA[3]]></column_4>
		<column_5><![CDATA[612.49]]></column_5>
	</node>
	<node>
		<column_1><![CDATA[Metropaed suspension 60ml]]></column_1>
		<column_2><![CDATA[Metronidazole 200mg]]></column_2>
		<column_3><![CDATA[Clarion]]></column_3>
		<column_4><![CDATA[3]]></column_4>
		<column_5><![CDATA[139.2]]></column_5>
	</node>
	<node>
		<column_1><![CDATA[Metrotab tablets 10]]></column_1>
		<column_2><![CDATA[Metronidazole 400mg]]></column_2>
		<column_3><![CDATA[Clarion]]></column_3>
		<column_4><![CDATA[3]]></column_4>
		<column_5><![CDATA[306.24]]></column_5>
	</node>
	<node>
		<column_1><![CDATA[Metrotab 200 tablets 10]]></column_1>
		<column_2><![CDATA[Metronidazole 200mg]]></column_2>
		<column_3><![CDATA[Clarion]]></column_3>
		<column_4><![CDATA[3]]></column_4>
		<column_5><![CDATA[218.75]]></column_5>
	</node>
	<node>
		<column_1><![CDATA[Metrotab 200 tablets 1000]]></column_1>
		<column_2><![CDATA[Metronidazole 200mg]]></column_2>
		<column_3><![CDATA[Clarion]]></column_3>
		<column_4><![CDATA[3]]></column_4>
		<column_5><![CDATA[1437.09]]></column_5>
	</node>
	<node>
		<column_1><![CDATA[Nova-3-sulfa  500]]></column_1>
		<column_2><![CDATA[Sulphathiazole 185mg, Sulphadiazine 185mg, Sulphamerazine 130mg]]></column_2>
		<column_3><![CDATA[Clarion]]></column_3>
		<column_4><![CDATA[3]]></column_4>
		<column_5><![CDATA[3368.68]]></column_5>
	</node>
	<node>
		<column_1><![CDATA[Cefax injection]]></column_1>
		<column_2><![CDATA[Ceftriaxone 1g]]></column_2>
		<column_3><![CDATA[Clarion]]></column_3>
		<column_4><![CDATA[3]]></column_4>
		<column_5><![CDATA[662.87]]></column_5>
	</node>
	<node>
		<column_1><![CDATA[Cefax injection]]></column_1>
		<column_2><![CDATA[Ceftriaxone 500mg]]></column_2>
		<column_3><![CDATA[Clarion]]></column_3>
		<column_4><![CDATA[3]]></column_4>
		<column_5><![CDATA[530.29]]></column_5>
	</node>
	<node>
		<column_1><![CDATA[Clavatin Bio-suspension 100ml]]></column_1>
		<column_2><![CDATA[Amoxycillin 200mg]]></column_2>
		<column_3><![CDATA[Clarion]]></column_3>
		<column_4><![CDATA[3]]></column_4>
		<column_5><![CDATA[662.87]]></column_5>
	</node>
	<node>
		<column_1><![CDATA[Pharmaclav 625 Tablet 14]]></column_1>
		<column_2><![CDATA[Amoxicillin 500mg, Clavulinic acid]]></column_2>
		<column_3><![CDATA[Clarion]]></column_3>
		<column_4><![CDATA[9]]></column_4>
		<column_5><![CDATA[720]]></column_5>
	</node>
	<node>
		<column_1><![CDATA[Pharmoxime tablets 10]]></column_1>
		<column_2><![CDATA[Cefuroxime 500mg]]></column_2>
		<column_3><![CDATA[Clarion]]></column_3>
		<column_4><![CDATA[9]]></column_4>
		<column_5><![CDATA[840]]></column_5>
	</node>
</data>
